hermalog/__init__.py
hermalog/configurations.py
hermalog/customLogging.py
hermalog/loggingBasic.py
hermalog/simpleLogging.py
hermalog-0.1.0.dist-info/METADATA
hermalog-0.1.0.dist-info/WHEEL
hermalog-0.1.0.dist-info/licenses/LICENSE
hermalog-0.1.0.dist-info/RECORD
