Metadata-Version: 2.3
Name: hermalog
Version: 0.1.0
Summary: A simple logging library for Python
Author-email: Chinmay Shah <hi@chinmayshah.xyz>
License-File: LICENSE
Requires-Python: >=3.8
